{
  "P6": { "name": "head of government" },
  "P17": { "name": "country" },
  "P18": { "name": "image" },
  "P31": { "name": "instance of" },
  "P36": { "name": "capital" },
  "P41": { "name": "flag image" },
  "P47": { "name": "shares border with" },
  "P94": { "name": "coat of arms image" },
  "P131": { "name": "located in the administrative territorial entity" },
  "P138": { "name": "named after" },
  "P150": { "name": "contains the administrative territorial entity" },
  "P155": { "name": "follows" },
  "P156": { "name": "followed by" },
  "P163": { "name": "flag" },
  "P190": { "name": "twinned administrative body" },
  "P206": { "name": "located in or next to body of water" },
  "P214": { "name": "VIAF ID" },
  "P227": { "name": "GND ID" },
  "P237": { "name": "coat of arms" },
  "P242": { "name": "locator map image" },
  "P244": { "name": "Library of Congress authority ID" },
  "P268": { "name": "Bibliothèque nationale de France ID" },
  "P269": { "name": "IdRef ID" },
  "P281": { "name": "postal code" },
  "P300": { "name": "ISO 3166-2 code" },
  "P361": { "name": "part of" },
  "P373": { "name": "Commons category" },
  "P402": { "name": "OpenStreetMap relation ID" },
  "P417": { "name": "patron saint" },
  "P421": { "name": "located in time zone" },
  "P460": { "name": "said to be the same as" },
  "P473": { "name": "local dialing code" },
  "P527": { "name": "has part(s)" },
  "P571": { "name": "inception" },
  "P576": { "name": "dissolved, abolished or demolished date" },
  "P625": { "name": "coordinate location" },
  "P646": { "name": "Freebase ID" },
  "P691": { "name": "NKCR AUT ID" },
  "P768": { "name": "electoral district" },
  "P856": { "name": "official website" },
  "P901": { "name": "FIPS 10-4 (countries and regions) " },
  "P910": { "name": "topic's main category" },
  "P935": { "name": "Commons gallery" },
  "P939": { "name": "KSH code" },
  "P948": { "name": "page banner" },
  "P982": { "name": "MusicBrainz area ID" },
  "P1036": { "name": "Dewey Decimal Classification" },
  "P1082": { "name": "population" },
  "P1151": { "name": "topic's main Wikimedia portal " },
  "P1245": { "name": "OmegaWiki Defined Meaning" },
  "P1249": { "name": "time of earliest written record" },
  "P1281": { "name": "WOEID" },
  "P1343": { "name": "described by source" },
  "P1365": { "name": "replaces" },
  "P1366": { "name": "replaced by" },
  "P1376": { "name": "capital of" },
  "P1383": { "name": "contains settlement" },
  "P1417": { "name": "Encyclopædia Britannica Online ID" },
  "P1424": { "name": "topic's main template" },
  "P1448": { "name": "official name" },
  "P1464": { "name": "category for people born here" },
  "P1465": { "name": "category for people who died here" },
  "P1566": { "name": "GeoNames ID" },
  "P1667": { "name": "Getty Thesaurus of Geographic Names ID" },
  "P1705": { "name": "native label" },
  "P1792": { "name": "category of associated people" },
  "P1813": { "name": "short name" },
  "P1889": { "name": "different from" },
  "P1958": { "name": "Trismegistos Geo ID" },
  "P1997": { "name": "Facebook Places ID" },
  "P2044": { "name": "elevation above sea level" },
  "P2046": { "name": "area" },
  "P2671": { "name": "Google Knowledge Graph ID" },
  "P3222": { "name": "NE.se ID" },
  "P3417": { "name": "Quora topic ID" },
  "P3896": { "name": "geoshape" },
  "P5353": { "name": "school district" },
  "P5573": { "name": "archINFORM location ID" },
  "P5901": { "name": "official number of town quarter" },
  "P6706": { "name": "De Agostini ID" },
  "P6766": { "name": "Who's on First ID" },
  "P6987": { "name": "Hungarian National Namespace place ID" },
  "P7305": { "name": "Online PWN Encyclopedia ID" },
  "P7471": { "name": "iNaturalist place ID" },
  "P7859": { "name": "WorldCat Identities ID" },
  "P7938": { "name": "associated electoral district" },
  "P7867": { "name": "category for maps" },
  "P8119": { "name": "HASC" },
  "P8168": { "name": "FactGrid item ID" },
  "P8189": { "name": "National Library of Israel J9U ID" },
  "P8592": { "name": "aerial view" },
  "P8989": { "name": "category for the view of the item" },
  "P9498": { "name": "Enzyklopädie des europäischen Ostens ID" },
  "P10280": { "name": "category for honorary citizens of entity" }
}
